<routes>
	<vehicle depart="0.1" departLane="0" departPos="69.68650380751052" departSpeed="7.130267799735405" id="201" type="passenger">
		<route edges="49574 gneE2 -gneE0 49576" />
	</vehicle>
	<vehicle depart="0.1" departLane="0" departPos="8.665252999986166" departSpeed="8.331440432641646" id="202" type="passenger">
		<route edges="49574 gneE2 -gneE0 49576" />
	</vehicle>
	<vehicle depart="0.1" departLane="0" departPos="63.54229011567791" departSpeed="6.371069619264884" id="203" type="passenger">
		<route edges="49578 gneE0 -gneE3 49568" />
	</vehicle>
	<vehicle depart="0.1" departLane="0" departPos="110.53803852337397" departSpeed="7.274102896645588" id="204" type="passenger">
		<route edges="49564 gneE1 -gneE2 49572" />
	</vehicle>
	<vehicle depart="0.1" departLane="0" departPos="86.77274438565073" departSpeed="7.339067210875362" id="205" type="passenger">
		<route edges="49564 gneE1 -gneE3 49568" />
	</vehicle>
</routes>