<routes>
	<vehicle depart="0.1" departLane="0" departPos="74.0226173804047" departSpeed="6.677987207217304" id="201" type="passenger">
		<route edges="49578 gneE0 -gneE3 49568" />
	</vehicle>
	<vehicle depart="0.1" departLane="0" departPos="51.64245305527125" departSpeed="6.700981750064102" id="202" type="passenger">
		<route edges="49578 gneE0 -gneE3 49568" />
	</vehicle>
	<vehicle depart="0.1" departLane="0" departPos="69.72033431258876" departSpeed="7.157964548483856" id="203" type="passenger">
		<route edges="49564 gneE1 -gneE2 49572" />
	</vehicle>
</routes>